truststore/__init__.py
truststore/_api.py
truststore/_macos.py
truststore/_openssl.py
truststore/_ssl_constants.py
truststore/_windows.py
truststore/py.typed
robocorp_truststore-0.9.1.dist-info/LICENSE
robocorp_truststore-0.9.1.dist-info/WHEEL
robocorp_truststore-0.9.1.dist-info/METADATA
robocorp_truststore-0.9.1.dist-info/RECORD
