Metadata-Version: 2.1
Name: robocorp-truststore
Version: 0.9.1
Summary: Verify certificates using native system trust stores
Author-email: Seth Michael Larson <sethmichaellarson@gmail.com>, David Glick <david@glicksoftware.com>
Requires-Python: >= 3.10
Classifier: Development Status :: 5 - Production/Stable
Classifier: Intended Audience :: Developers
Classifier: License :: OSI Approved :: MIT License
Classifier: Operating System :: MacOS
Classifier: Operating System :: Microsoft
Classifier: Programming Language :: Python :: 3
Classifier: Programming Language :: Python :: 3 :: Only
Classifier: Programming Language :: Python :: 3.10
Classifier: Programming Language :: Python :: 3.11
Classifier: Programming Language :: Python :: 3.12
Classifier: Programming Language :: Python :: 3.13
Classifier: Programming Language :: Python :: Implementation :: CPython
Classifier: Programming Language :: Python :: Implementation :: PyPy
Project-URL: Documentation, https://truststore.readthedocs.io
Project-URL: Source, https://github.com/robocorp/truststore
